LICENSE-MIT
MANIFEST.in
README.rst
setup.py
value.py
value.egg-info/PKG-INFO
value.egg-info/SOURCES.txt
value.egg-info/dependency_links.txt
value.egg-info/top_level.txt