Metadata-Version: 1.1
Name: value
Version: 0.1.0
Summary: Implementation of Value Object pattern
Home-page: http://github.com/halst/value
Author: Vladimir Keleshev
Author-email: vladimir@keleshev.com
License: MIT
Keywords: value object pattern
Platform: UNKNOWN
Classifier: Development Status :: 3 - Alpha
Classifier: Topic :: Utilities
Classifier: Programming Language :: Python :: 2.5
Classifier: Programming Language :: Python :: 2.6
Classifier: Programming Language :: Python :: 2.7
Classifier: Programming Language :: Python :: 3.2
Classifier: Programming Language :: Python :: 3.3
Classifier: License :: OSI Approved :: MIT License
